support/__init__.py
support/admin.py
support/apps.py
support/checks.py
support/consumers.py
support/filters.py
support/migrations/0001_initial.py
support/migrations/0002_alter_ticket_options_remove_message_viewed_and_more.py
support/migrations/__init__.py
support/models.py
support/routing.py
support/serializers.py
support/signals.py
support/static/support/css/style.css
support/static/support/js/const/API_URL.js
support/static/support/js/const/ELEMENTS.js
support/static/support/js/const/SOCKET_URL.js
support/static/support/js/const/TICKETS_EVENTS.js
support/static/support/js/helpers/addTicketToList.js
support/static/support/js/helpers/appendMessageToChat.js
support/static/support/js/helpers/createElement.js
support/static/support/js/helpers/createMessage.js
support/static/support/js/helpers/getCookieByName.js
support/static/support/js/helpers/renderMessageList.js
support/static/support/js/helpers/updateMessageViewStatus.js
support/static/support/js/helpers/updateTicketAssignment.js
support/static/support/js/index.js
support/static/support/js/scripts/apiController.js
support/static/support/js/scripts/socketController.js
support/static/support/js/state.js
support/templates/support/support_manager.html
support/urls.py
support/views.py
chatlabs_django_support-1.2.0.dist-info/METADATA
chatlabs_django_support-1.2.0.dist-info/WHEEL
chatlabs_django_support-1.2.0.dist-info/RECORD
