Metadata-Version: 2.4
Name: chatlabs-django-support
Version: 1.2.0
Summary: 
Author: Rostislaww
Author-email: rostiki.com@mail.ru
Requires-Python: >=3.11,<4.0
Classifier: Programming Language :: Python :: 3
Classifier: Programming Language :: Python :: 3.11
Classifier: Programming Language :: Python :: 3.12
Classifier: Programming Language :: Python :: 3.13
Classifier: Programming Language :: Python :: 3.14
Requires-Dist: Django (==5.0.1)
Requires-Dist: channels (>=4.2.0,<5.0.0)
Requires-Dist: daphne (>=4.1.2,<5.0.0)
Requires-Dist: django-filter (>=25.1,<26.0)
Requires-Dist: djangorestframework (>=3.15.2,<4.0.0)
Project-URL: Homepage, https://github.com/RostHarcha/chatlabs-django-support
